cynapse/__init__.py
cynapse/async_monitor.py
cynapse/decorators.py
cynapse/exceptions.py
cynapse/models.py
cynapse/monitor.py
cynapse/core/__init__.py
cynapse/core/baseline.py
cynapse/core/bytecode.py
cynapse/core/hash_engine.py
cynapse/core/healer.py
cynapse/core/merkle.py
cynapse/core/verifier.py
cynapse/detection/__init__.py
cynapse/detection/monkey_patch.py
cynapse/integrations/__init__.py
cynapse/integrations/django.py
cynapse/integrations/fastapi.py
cynapse/integrations/flask.py
cynapse/introspection/__init__.py
cynapse/introspection/imports.py
cynapse/introspection/modules.py
cynapse/platform/__init__.py
cynapse/platform/base.py
cynapse/platform/factory.py
cynapse/platform/linux.py
cynapse/platform/macos.py
cynapse/platform/windows.py
cynapse/response/__init__.py
cynapse/testing/__init__.py
cynapse/testing/tamper.py
cynapse/utils/__init__.py
cynapse/utils/config.py
cynapse-1.0.0.dist-info/licenses/LICENSE
docs/HANDOFF.md
docs/INSTALLATION.md
docs/QUICKSTART.md
docs/design.md
examples/README.md
examples/async_example.py
examples/basic_usage.py
examples/context_manager.py
examples/custom_handler.py
examples/decorator_protection.py
examples/detection_demo.py
examples/flask_app.py
report/01_Executive Summary.md
report/02_Introduction.md
report/03_System Overview.md
report/04_Requirements Analysis.md
report/05_System Design.md
report/06_Technology Stack.md
report/07_Implementation.md
report/08_Testing and Quality Assurance.md
report/09_Deployment.md
report/10_Security Considerations.md
report/11_Performance Analysis.md
report/12_Maintenance and Updates.md
report/13_User Documentation.md
report/14_Project Management.md
report/15_Evaluation and Feedback.md
report/16_Future Enhancements.md
report/17_Conclusion.md
report/18_References.md
report/19_Appendices.md
tests/__init__.py
tests/test_baseline.py
tests/test_bytecode.py
tests/test_decorators.py
tests/test_hash_engine.py
tests/test_monitor.py
cynapse-1.0.0.dist-info/METADATA
cynapse-1.0.0.dist-info/WHEEL
cynapse-1.0.0.dist-info/top_level.txt
cynapse-1.0.0.dist-info/RECORD
