Metadata-Version: 2.4
Name: cynapse
Version: 1.0.0
Summary: Real-time memory integrity monitor for Python
Author-email: Tonmoy Infrastructure & Vision OSS <oss@tivision.dev>
License: MIT
Project-URL: Homepage, https://gitlab.com/TIVisionOSS/python/cynapse
Project-URL: Documentation, https://cynapse.readthedocs.io
Project-URL: Repository, https://gitlab.com/TIVisionOSS/python/cynapse
Project-URL: Issues, https://gitlab.com/TIVisionOSS/python/cynapse/-/issues
Keywords: security,integrity,monitoring,runtime,protection,tamper-detection
Classifier: Development Status :: 4 - Beta
Classifier: Intended Audience :: Developers
Classifier: License :: OSI Approved :: MIT License
Classifier: Programming Language :: Python :: 3
Classifier: Programming Language :: Python :: 3.8
Classifier: Programming Language :: Python :: 3.9
Classifier: Programming Language :: Python :: 3.10
Classifier: Programming Language :: Python :: 3.11
Classifier: Programming Language :: Python :: 3.12
Classifier: Programming Language :: Python :: 3.13
Classifier: Operating System :: OS Independent
Classifier: Operating System :: POSIX :: Linux
Classifier: Operating System :: Microsoft :: Windows
Classifier: Operating System :: MacOS
Classifier: Topic :: Security
Classifier: Topic :: Software Development :: Libraries :: Python Modules
Requires-Python: >=3.8
License-File: LICENSE
Provides-Extra: blake3
Requires-Dist: blake3>=0.3.0; extra == "blake3"
Provides-Extra: dev
Requires-Dist: pytest>=7.0.0; extra == "dev"
Requires-Dist: pytest-cov>=4.0.0; extra == "dev"
Requires-Dist: pytest-asyncio>=0.21.0; extra == "dev"
Requires-Dist: black>=23.0.0; extra == "dev"
Requires-Dist: isort>=5.12.0; extra == "dev"
Requires-Dist: mypy>=1.0.0; extra == "dev"
Requires-Dist: ruff>=0.1.0; extra == "dev"
Requires-Dist: psutil>=5.9.0; extra == "dev"
Provides-Extra: flask
Requires-Dist: flask>=2.0.0; extra == "flask"
Provides-Extra: django
Requires-Dist: django>=3.2.0; extra == "django"
Provides-Extra: fastapi
Requires-Dist: fastapi>=0.100.0; extra == "fastapi"
Provides-Extra: all
Requires-Dist: blake3>=0.3.0; extra == "all"
Requires-Dist: flask>=2.0.0; extra == "all"
Requires-Dist: django>=3.2.0; extra == "all"
Requires-Dist: fastapi>=0.100.0; extra == "all"
Requires-Dist: psutil>=5.9.0; extra == "all"
Dynamic: license-file
